boring_news_mcp/__init__.py
boring_news_mcp/__main__.py
boring_news_mcp/client.py
boring_news_mcp-0.5.4.dist-info/METADATA
boring_news_mcp-0.5.4.dist-info/WHEEL
boring_news_mcp-0.5.4.dist-info/entry_points.txt
boring_news_mcp-0.5.4.dist-info/RECORD
