Metadata-Version: 2.4
Name: boring-news-mcp
Version: 0.5.4
Summary: MCP (Model Context Protocol) Server for Boring News API
Project-URL: Homepage, https://github.com/oliviergg/boring-news-mcp
Author: Boring News Team
License-Expression: MIT
Requires-Python: >=3.10
Requires-Dist: fastmcp>=0.1.0
Requires-Dist: httpx>=0.25.0
